mkvstrip.py
mkvstrip-1.0.2.dist-info/METADATA
mkvstrip-1.0.2.dist-info/RECORD
mkvstrip-1.0.2.dist-info/WHEEL
mkvstrip-1.0.2.dist-info/entry_points.txt
mkvstrip-1.0.2.dist-info/top_level.txt
