Metadata-Version: 2.1
Name: mkvstrip
Version: 1.0.2
Summary: Python script, that acts as a front end for mkvtoolnix to removeexcess audio and subtitle streams from mkv files.
Home-page: https://github.com/willforde/mkvstrip
Author: William Forde
Author-email: willforde@gmail.com
License: UNKNOWN
Keywords: mkv mkvmerge mkvtoolnix
Platform: OS Independent
Classifier: Development Status :: 5 - Production/Stable
Classifier: Intended Audience :: End Users/Desktop
Classifier: Operating System :: OS Independent
Classifier: Environment :: Console
Classifier: Programming Language :: Python :: 3
Classifier: Programming Language :: Python :: 3.4
Classifier: Programming Language :: Python :: 3.5
Classifier: Programming Language :: Python :: 3.6
Classifier: Programming Language :: Python :: 3 :: Only
Classifier: Topic :: Multimedia :: Sound/Audio
Classifier: Topic :: Multimedia :: Video
Classifier: Topic :: Utilities
Classifier: License :: OSI Approved :: GNU General Public License v3 (GPLv3)
Requires-Python: >=3.4.0
